{"responses":[{"items":[{"commentCount":0,"id":"UCRW3VLiVep5Ud4Ovhj2eUyA","snippet":{"description":"Мастерская Настроения - канал который сделает ваш день лучше!","publishedAt":"2013-08-10T15:04:53.000Z","thumbnails":{"high":{"height":0,"url":"https://yt3.ggpht.com/-qBeOy-61oQI/AAAAAAAAAAI/AAAAAAAAAAA/GHyFcvXdBW8/s240-c-k-no-mo-rj-c0xffffff/photo.jpg","width":0},"medium":{"height":0,"url":"https://yt3.ggpht.com/-qBeOy-61oQI/AAAAAAAAAAI/AAAAAAAAAAA/GHyFcvXdBW8/s240-c-k-no-mo-rj-c0xffffff/photo.jpg","width":0}},"title":"Мастерская Настроения"},"statistics":{"commentCount":"0","subscriberCount":"4554953","videoCount":"351","viewCount":"937849566"}}]},{"items":[{"commentCount":0,"id":"UC6zhI71atP7YLoZyIyCIGNw","snippet":{"description":"“Dave and Ava Nursery Rhymes” is animated series developed especially for young children, ages 1-6. \n\nEach episode features Dave - a boy dressed as a puppy, and Ava - a girl dressed as a kitten, along with their friends – Matilda the Sheep, Oscar the Kitten, Stella the Star, cute little mouse Philip, Itsy the Spider, Felix MacDonald, Bingo the Puppy, Izzy the Cat and many more.\n\nOur nursery rhymes teach little ones ABCs, numbers, shapes, colors, and more!  Little ones learn to focus and play independently. You can relax for a moment - Dave and Ava will entertain your children while teaching them favorite nursery rhymes.\n\nThe videos are also available to download and watch offline via iOS app https://goo.gl/6gKEvU and Android app https://goo.gl/75fcw4 or at bamazoo.com/daveandava.","publishedAt":"2014-12-04T09:22:53.000Z","thumbnails":{"high":{"height":0,"url":"https://yt3.ggpht.com/-CTsoKK460BI/AAAAAAAAAAI/AAAAAAAAAAA/eHHeHP6JAgs/s240-c-k-no-mo-rj-c0xffffff/photo.jpg","width":0},"medium":{"height":0,"url":"https://yt3.ggpht.com/-CTsoKK460BI/AAAAAAAAAAI/AAAAAAAAAAA/eHHeHP6JAgs/s240-c-k-no-mo-rj-c0xffffff/photo.jpg","width":0}},"title":"Dave and Ava - Nursery Rhymes and Baby Songs"},"statistics":{"commentCount":"0","subscriberCount":"2770182","videoCount":"299","viewCount":"1723193593"}}]}]}